{
    "mal-id": 18689,
    "anilist-id": 18689,
    "anilist-name_en": "Ace of the Diamond",
    "anilist-name_jp": "Diamond no Ace",
    "afl-name": "Ace of the Diamond",
    "afl-link": "https://www.animefillerlist.com/shows/ace-diamond",
    "fillers_episodes": [
        "28",
        "76",
        "77",
        "78"
    ],
    "episodes": [
        {
            "title": "The One Pitch",
            "number": "1",
            "filler": "Manga Canon",
            "filler-bool": false
        },
        {
            "title": "Partner",
            "number": "2",
            "filler": "Manga Canon",
            "filler-bool": false
        },
        {
            "title": "Not Qualified to Be a Pitcher?",
            "number": "3",
            "filler": "Manga Canon",
            "filler-bool": false
        },
        {
            "title": "Are You Like Me?",
            "number": "4",
            "filler": "Manga Canon",
            "filler-bool": false
        },
        {
            "title": "A Clash",
            "number": "5",
            "filler": "Manga Canon",
            "filler-bool": false
        },
        {
            "title": "Head to Head!",
            "number": "6",
            "filler": "Manga Canon",
            "filler-bool": false
        },
        {
            "title": "The Two Batteries",
            "number": "7",
            "filler": "Manga Canon",
            "filler-bool": false
        },
        {
            "title": "The Truth About Chris",
            "number": "8",
            "filler": "Manga Canon",
            "filler-bool": false
        },
        {
            "title": "With Chagrin in His Heart",
            "number": "9",
            "filler": "Manga Canon",
            "filler-bool": false
        },
        {
            "title": "Hone Your Moving Fastball",
            "number": "10",
            "filler": "Manga Canon",
            "filler-bool": false
        },
        {
            "title": "Chris to the Field!",
            "number": "11",
            "filler": "Manga Canon",
            "filler-bool": false
        },
        {
            "title": "Target",
            "number": "12",
            "filler": "Manga Canon",
            "filler-bool": false
        },
        {
            "title": "You\u2019re in the First-String",
            "number": "13",
            "filler": "Manga Canon",
            "filler-bool": false
        },
        {
            "title": "Training Camp Begins!",
            "number": "14",
            "filler": "Manga Canon",
            "filler-bool": false
        },
        {
            "title": "Lead With Your Plays!",
            "number": "15",
            "filler": "Manga Canon",
            "filler-bool": false
        },
        {
            "title": "Challenge",
            "number": "16",
            "filler": "Manga Canon",
            "filler-bool": false
        },
        {
            "title": "Games Are Fun",
            "number": "17",
            "filler": "Manga Canon",
            "filler-bool": false
        },
        {
            "title": "I Hate It, But....",
            "number": "18",
            "filler": "Manga Canon",
            "filler-bool": false
        },
        {
            "title": "Fate",
            "number": "19",
            "filler": "Manga Canon",
            "filler-bool": false
        },
        {
            "title": "Emergency",
            "number": "20",
            "filler": "Manga Canon",
            "filler-bool": false
        },
        {
            "title": "To the Dream Stage",
            "number": "21",
            "filler": "Manga Canon",
            "filler-bool": false
        },
        {
            "title": "Calling for Attention",
            "number": "22",
            "filler": "Manga Canon",
            "filler-bool": false
        },
        {
            "title": "Official Game Debut",
            "number": "23",
            "filler": "Manga Canon",
            "filler-bool": false
        },
        {
            "title": "Clockwork",
            "number": "24",
            "filler": "Manga Canon",
            "filler-bool": false
        },
        {
            "title": "Anti-Furuya Strategy",
            "number": "25",
            "filler": "Manga Canon",
            "filler-bool": false
        },
        {
            "title": "Miracle Akikawa",
            "number": "26",
            "filler": "Manga Canon",
            "filler-bool": false
        },
        {
            "title": "I\u2019m Not Running",
            "number": "27",
            "filler": "Manga Canon",
            "filler-bool": false
        },
        {
            "title": "Path, Eijun Sawamura to the Scorching Mound",
            "number": "28",
            "filler": "Filler",
            "filler-bool": true
        },
        {
            "title": "Neck and Neck",
            "number": "29",
            "filler": "Manga Canon",
            "filler-bool": false
        },
        {
            "title": "Winner and Loser",
            "number": "30",
            "filler": "Manga Canon",
            "filler-bool": false
        },
        {
            "title": "Dark Horse",
            "number": "31",
            "filler": "Manga Canon",
            "filler-bool": false
        },
        {
            "title": "Summers",
            "number": "32",
            "filler": "Manga Canon",
            "filler-bool": false
        },
        {
            "title": "Money Tree",
            "number": "33",
            "filler": "Manga Canon",
            "filler-bool": false
        },
        {
            "title": "Reliable Teammates",
            "number": "34",
            "filler": "Manga Canon",
            "filler-bool": false
        },
        {
            "title": "Potential",
            "number": "35",
            "filler": "Manga Canon",
            "filler-bool": false
        },
        {
            "title": "The Ace Walks On",
            "number": "36",
            "filler": "Manga Canon",
            "filler-bool": false
        },
        {
            "title": "Burst!",
            "number": "37",
            "filler": "Manga Canon",
            "filler-bool": false
        },
        {
            "title": "Roles",
            "number": "38",
            "filler": "Manga Canon",
            "filler-bool": false
        },
        {
            "title": "Expectations of an Ace",
            "number": "39",
            "filler": "Manga Canon",
            "filler-bool": false
        },
        {
            "title": "The Winning Shot",
            "number": "40",
            "filler": "Manga Canon",
            "filler-bool": false
        },
        {
            "title": "It\u2019s the Semifinal",
            "number": "41",
            "filler": "Manga Canon",
            "filler-bool": false
        },
        {
            "title": "The Giant Looks Down",
            "number": "42",
            "filler": "Manga Canon",
            "filler-bool": false
        },
        {
            "title": "Revenge",
            "number": "43",
            "filler": "Manga Canon",
            "filler-bool": false
        },
        {
            "title": "Best Pitch",
            "number": "44",
            "filler": "Manga Canon",
            "filler-bool": false
        },
        {
            "title": "Pitching of Despair",
            "number": "45",
            "filler": "Manga Canon",
            "filler-bool": false
        },
        {
            "title": "Fantasy",
            "number": "46",
            "filler": "Manga Canon",
            "filler-bool": false
        },
        {
            "title": "That Summer",
            "number": "47",
            "filler": "Manga Canon",
            "filler-bool": false
        },
        {
            "title": "At the Dorm...",
            "number": "48",
            "filler": "Manga Canon",
            "filler-bool": false
        },
        {
            "title": "A Nostalgic Face",
            "number": "49",
            "filler": "Manga Canon",
            "filler-bool": false
        },
        {
            "title": "Footsteps to Tomorrow",
            "number": "50",
            "filler": "Manga Canon",
            "filler-bool": false
        },
        {
            "title": "The Battle Begins!",
            "number": "51",
            "filler": "Manga Canon",
            "filler-bool": false
        },
        {
            "title": "I Don\u2019t Want to Lose",
            "number": "52",
            "filler": "Manga Canon",
            "filler-bool": false
        },
        {
            "title": "Change Gears",
            "number": "53",
            "filler": "Manga Canon",
            "filler-bool": false
        },
        {
            "title": "Entrusted Faith and the Courage to Perform",
            "number": "54",
            "filler": "Manga Canon",
            "filler-bool": false
        },
        {
            "title": "Strong Men",
            "number": "55",
            "filler": "Manga Canon",
            "filler-bool": false
        },
        {
            "title": "Decision",
            "number": "56",
            "filler": "Manga Canon",
            "filler-bool": false
        },
        {
            "title": "Reliable Underclassmen",
            "number": "57",
            "filler": "Manga Canon",
            "filler-bool": false
        },
        {
            "title": "The Three-Hole",
            "number": "58",
            "filler": "Manga Canon",
            "filler-bool": false
        },
        {
            "title": "Fearless",
            "number": "59",
            "filler": "Manga Canon",
            "filler-bool": false
        },
        {
            "title": "Lonely Sun",
            "number": "60",
            "filler": "Manga Canon",
            "filler-bool": false
        },
        {
            "title": "Determined",
            "number": "61",
            "filler": "Manga Canon",
            "filler-bool": false
        },
        {
            "title": "Victory or Defeat",
            "number": "62",
            "filler": "Manga Canon",
            "filler-bool": false
        },
        {
            "title": "Lingering Feelings",
            "number": "63",
            "filler": "Manga Canon",
            "filler-bool": false
        },
        {
            "title": "Restart",
            "number": "64",
            "filler": "Manga Canon",
            "filler-bool": false
        },
        {
            "title": "In the Sun",
            "number": "65",
            "filler": "Manga Canon",
            "filler-bool": false
        },
        {
            "title": "Outsider",
            "number": "66",
            "filler": "Manga Canon",
            "filler-bool": false
        },
        {
            "title": "The Kick",
            "number": "67",
            "filler": "Manga Canon",
            "filler-bool": false
        },
        {
            "title": "The Ace Title",
            "number": "68",
            "filler": "Manga Canon",
            "filler-bool": false
        },
        {
            "title": "Can\u2019t Lose!",
            "number": "69",
            "filler": "Manga Canon",
            "filler-bool": false
        },
        {
            "title": "Next Stage",
            "number": "70",
            "filler": "Manga Canon",
            "filler-bool": false
        },
        {
            "title": "September Sky",
            "number": "71",
            "filler": "Manga Canon",
            "filler-bool": false
        },
        {
            "title": "The Final Lesson",
            "number": "72",
            "filler": "Manga Canon",
            "filler-bool": false
        },
        {
            "title": "Inheritance",
            "number": "73",
            "filler": "Manga Canon",
            "filler-bool": false
        },
        {
            "title": "The Guiding Light",
            "number": "74",
            "filler": "Manga Canon",
            "filler-bool": false
        },
        {
            "title": "In Pursuit",
            "number": "75",
            "filler": "Manga Canon",
            "filler-bool": false
        },
        {
            "title": "Howling in the Summer",
            "number": "76",
            "filler": "Filler",
            "filler-bool": true
        },
        {
            "title": "The Summer Heat Haze",
            "number": "77",
            "filler": "Filler",
            "filler-bool": true
        },
        {
            "title": "The Kings of Summer",
            "number": "78",
            "filler": "Filler",
            "filler-bool": true
        },
        {
            "title": "The Fall Tournament Begins!",
            "number": "79",
            "filler": "Manga Canon",
            "filler-bool": false
        },
        {
            "title": "The Cold Rain",
            "number": "80",
            "filler": "Manga Canon",
            "filler-bool": false
        },
        {
            "title": "Out of Order",
            "number": "81",
            "filler": "Manga Canon",
            "filler-bool": false
        },
        {
            "title": "Where I Am",
            "number": "82",
            "filler": "Manga Canon",
            "filler-bool": false
        },
        {
            "title": "Scenario",
            "number": "83",
            "filler": "Manga Canon",
            "filler-bool": false
        },
        {
            "title": "My Path",
            "number": "84",
            "filler": "Manga Canon",
            "filler-bool": false
        },
        {
            "title": "Did You Just Pitch...",
            "number": "85",
            "filler": "Manga Canon",
            "filler-bool": false
        },
        {
            "title": "The Underdog Story",
            "number": "86",
            "filler": "Manga Canon",
            "filler-bool": false
        },
        {
            "title": "Self-Destruction",
            "number": "87",
            "filler": "Manga Canon",
            "filler-bool": false
        },
        {
            "title": "Fissure",
            "number": "88",
            "filler": "Manga Canon",
            "filler-bool": false
        },
        {
            "title": "On My Shoulders",
            "number": "89",
            "filler": "Manga Canon",
            "filler-bool": false
        },
        {
            "title": "Persistent and Diligent",
            "number": "90",
            "filler": "Manga Canon",
            "filler-bool": false
        },
        {
            "title": "Chain Reaction",
            "number": "91",
            "filler": "Manga Canon",
            "filler-bool": false
        },
        {
            "title": "Shut Him Down!!",
            "number": "92",
            "filler": "Manga Canon",
            "filler-bool": false
        },
        {
            "title": "This Guy\u2019s Pretty Good",
            "number": "93",
            "filler": "Manga Canon",
            "filler-bool": false
        },
        {
            "title": "An Uncompromising Challenge",
            "number": "94",
            "filler": "Manga Canon",
            "filler-bool": false
        },
        {
            "title": "With Heads Held High",
            "number": "95",
            "filler": "Manga Canon",
            "filler-bool": false
        },
        {
            "title": "Whispers of the Devil?",
            "number": "96",
            "filler": "Manga Canon",
            "filler-bool": false
        },
        {
            "title": "Winging It",
            "number": "97",
            "filler": "Manga Canon",
            "filler-bool": false
        },
        {
            "title": "School Academic Level",
            "number": "98",
            "filler": "Manga Canon",
            "filler-bool": false
        },
        {
            "title": "Individual Minds",
            "number": "99",
            "filler": "Manga Canon",
            "filler-bool": false
        },
        {
            "title": "Zeal",
            "number": "100",
            "filler": "Manga Canon",
            "filler-bool": false
        },
        {
            "title": "The Conceited Underclassman",
            "number": "101",
            "filler": "Manga Canon",
            "filler-bool": false
        },
        {
            "title": "Step By Step",
            "number": "102",
            "filler": "Manga Canon",
            "filler-bool": false
        },
        {
            "title": "The Resilient Second-String",
            "number": "103",
            "filler": "Manga Canon",
            "filler-bool": false
        },
        {
            "title": "Demon Child",
            "number": "104",
            "filler": "Manga Canon",
            "filler-bool": false
        },
        {
            "title": "The Kings\u2019 Roar",
            "number": "105",
            "filler": "Manga Canon",
            "filler-bool": false
        },
        {
            "title": "The Courage He Gave Me",
            "number": "106",
            "filler": "Manga Canon",
            "filler-bool": false
        },
        {
            "title": "The Resolve for Responsibility",
            "number": "107",
            "filler": "Manga Canon",
            "filler-bool": false
        },
        {
            "title": "The Ace\u2019s Instinct",
            "number": "108",
            "filler": "Manga Canon",
            "filler-bool": false
        },
        {
            "title": "Innocent",
            "number": "109",
            "filler": "Manga Canon",
            "filler-bool": false
        },
        {
            "title": "The World Beyond",
            "number": "110",
            "filler": "Manga Canon",
            "filler-bool": false
        },
        {
            "title": "Rematch",
            "number": "111",
            "filler": "Manga Canon",
            "filler-bool": false
        },
        {
            "title": "Priorities",
            "number": "112",
            "filler": "Manga Canon",
            "filler-bool": false
        },
        {
            "title": "One Pitch",
            "number": "113",
            "filler": "Manga Canon",
            "filler-bool": false
        },
        {
            "title": "Meeting Expectations",
            "number": "114",
            "filler": "Manga Canon",
            "filler-bool": false
        },
        {
            "title": "Play Ball",
            "number": "115",
            "filler": "Manga Canon",
            "filler-bool": false
        },
        {
            "title": "The Lead-off Man",
            "number": "116",
            "filler": "Manga Canon",
            "filler-bool": false
        },
        {
            "title": "Fastball, Featuring Todoroki",
            "number": "117",
            "filler": "Manga Canon",
            "filler-bool": false
        },
        {
            "title": "To This Side",
            "number": "118",
            "filler": "Manga Canon",
            "filler-bool": false
        },
        {
            "title": "The Best Fastball",
            "number": "119",
            "filler": "Manga Canon",
            "filler-bool": false
        },
        {
            "title": "The Field",
            "number": "120",
            "filler": "Manga Canon",
            "filler-bool": false
        },
        {
            "title": "The Decision",
            "number": "121",
            "filler": "Manga Canon",
            "filler-bool": false
        },
        {
            "title": "Partnership",
            "number": "122",
            "filler": "Manga Canon",
            "filler-bool": false
        },
        {
            "title": "Party Boys",
            "number": "123",
            "filler": "Manga Canon",
            "filler-bool": false
        },
        {
            "title": "Just You Wait!",
            "number": "124",
            "filler": "Manga Canon",
            "filler-bool": false
        },
        {
            "title": "Last Inning",
            "number": "125",
            "filler": "Manga Canon",
            "filler-bool": false
        },
        {
            "title": "Seek Diamonds!",
            "number": "126",
            "filler": "Manga Canon",
            "filler-bool": false
        }
    ],
    "nextAiringEpisode": "Unknown",
    "total-episodes": 75
}